tests/__init__.py
tests/test_dirs_only.py
tests/test_dots.py
tests/test_os_fileops.py
tests/test_yamldir.py
tests/test_yamldirs_cmd.py
tests/test_yamldirs_import.py
tests/testpkg/__init__.py
tests/testpkg/foo.py
yamldirs/__init__.py
yamldirs/filemaker.py
yamldirs/yamldirs_cmd.py
yamldirs-1.1.16.dist-info/LICENSE
yamldirs-1.1.16.dist-info/METADATA
yamldirs-1.1.16.dist-info/WHEEL
yamldirs-1.1.16.dist-info/entry_points.txt
yamldirs-1.1.16.dist-info/top_level.txt
yamldirs-1.1.16.dist-info/RECORD
