Metadata-Version: 2.1
Name: yamldirs
Version: 1.1.16
Summary: yamldirs - create directories and files (incl. contents) from yaml spec.
Home-page: https://github.com/datakortet/yamldirs
Author: Bjorn Pettersen
Author-email: bp@datakortet.no
License: UNKNOWN
Platform: UNKNOWN
Classifier: Development Status :: 5 - Production/Stable
Classifier: Intended Audience :: Developers
Classifier: Programming Language :: Python
Classifier: Programming Language :: Python :: 2
Classifier: Programming Language :: Python :: 2.7
Classifier: Programming Language :: Python :: 3
Classifier: Programming Language :: Python :: 3.5
Classifier: Programming Language :: Python :: 3.6
Classifier: Programming Language :: Python :: 3.7
Classifier: Programming Language :: Python :: 3.8
Classifier: Topic :: Software Development :: Libraries
License-File: LICENSE
Requires-Dist: ruamel.yaml
